pyfusefilter/ffibuild.py
pyfusefilter/pyfusefilter.py
pyfusefilter/__init__.py
pyfusefilter/_xorfilter.abi3.so
tests/test_fuse8.py
tests/__init__.py
tests/test_xor16.py
tests/test_fuse16.py
tests/test_xor8.py
pyfusefilter-1.2.1.dist-info/METADATA
pyfusefilter-1.2.1.dist-info/LICENSE
pyfusefilter-1.2.1.dist-info/top_level.txt
pyfusefilter-1.2.1.dist-info/WHEEL
pyfusefilter-1.2.1.dist-info/RECORD
