Metadata-Version: 2.1
Name: pyfusefilter
Version: 1.2.1
Summary: Python bindings for C implementation of xor and fuse filters
Home-page: https://github.com/FastFilter/pyfusefilter
Author: Amey Narkhede & Daniel Lemire
Author-email: Amey Narkhede <ameynarkhede02@gmail.com>, Daniel Lemire <daniel@lemire.me>
License: Apache License
Project-URL: Homepage, https://github.com/FastFilter/pyfusefilter
Requires-Python: >=3.0
License-File: LICENSE
Requires-Dist: cffi
Requires-Dist: xxhash
